audit_dummy/README.md
audit_dummy/__init__.py
audit_dummy/append.py
audit_dummy/file.json
audit_dummy/query.py
audit_dummy/schema.py
audit_dummy/utils.py
audit_dummy-0.1.0.dist-info/WHEEL
audit_dummy-0.1.0.dist-info/METADATA
audit_dummy-0.1.0.dist-info/RECORD
