Metadata-Version: 2.1
Name: audit-dummy
Version: 0.1.0
Summary: 
Author: LukeBoyer
Author-email: boyer.l@husky.neu.edu
Requires-Python: >=3.9,<4.0
Classifier: Programming Language :: Python :: 3
Classifier: Programming Language :: Python :: 3.10
Classifier: Programming Language :: Python :: 3.9
Requires-Dist: graphene (==3.0)
